{
    "corsDomains" : [
      "data.amerigeoss.org"
    ],
      "initialCamera": {
          "west": -87.90078601160957,
          "south": -18.31791109872471,
          "east": -56.392394100907964,
          "north": 0.440330689920997,
          "position": {
              "x": 2833752.2281731796,
              "y": -8797919.38014849,
              "z": -1504883.1333470743
          },
          "direction": {
              "x": -0.30252380465724077,
              "y": 0.9392423294770615,
              "z": 0.16218259504093155
          },
          "up": {
              "x": 0.04972238203876038,
              "y": -0.1543725327206959,
              "z": 0.9867607642512897
          }
    },
    "baseMapName":"Bing Maps Roads",
      "homeCamera": {
          "west": -77.2,
          "south": -12.5,
          "east": -76.5,
          "north": -11.5
      },
      "catalog": [{
              "name": "Catalog",
              "type": "group",
              "order": 2,
              "description": "desc",
              "items": [
                  {
                  "name": "Ministerio del Ambiente",
                  "type": "group",
                  "items": [{
                      "name": "Biodiversity and Ecosystems",
                      "type": "group",
                      "items": [{
                              "name": "Protected Areas",
                              "type": "group",
                              "items": [{
                                  "name": "Conservation Areas",
                                  "type": "esri-mapServer",
                                  "url": "https://geoservidorperu.minam.gob.pe/arcgis/rest/services/ANP/MapServer"
                              },
                              {
                                  "name": "Image Catalog",
                                  "type": "esri-mapServer",
                                  "url": "https://geoservidorperu.minam.gob.pe/arcgis/rest/services/Catalogo_Imagenes/MapServer"
                              },
                              {
                                  "name": "Risk Scenarios in Piura",
                                  "type": "esri-mapServer",
                                  "url": "https://geoservidorperu.minam.gob.pe/arcgis/rest/services/Escenarios_riesgo_piura/MapServer"
                              }]
                          },
                          {
                              "name": "Coastal Ecosystem",
                              "type": "group",
                              "items": [{
                                  "name": "Marine Erosion",
                                  "type": "esri-mapServer",
                                  "url": "https://geoservidorperu.minam.gob.pe/arcgis/rest/services/ServicioGeocostaErosion/MapServer"
                              },
                              {
                                  "name": "Southeast Pacific data and Information Network in support to Integrated Coastal Area Management",
                                  "type": "esri-mapServer",
                                  "url": "https://geoservidorperu.minam.gob.pe/arcgis/rest/services/ServicioIndicadores/MapServer"
                              },
                              {
                                  "name": "Coastal Marine Ecosystem",
                                  "type": "esri-mapServer",
                                  "url": "https://geoservidorperu.minam.gob.pe/arcgis/rest/services/ServicioGeocostaEcosistema/MapServer"
                              }
                              ]
                          },
                          {
                              "name": "Vegetation and Land Cover",
                              "type": "group",
                              "items": [{
                                  "name": "Carbon",
                                  "type": "esri-mapServer",
                                  "url": "https://geoservidorperu.minam.gob.pe/arcgis/rest/services/ServicioCarbono/MapServer"
                              }]
                          }
                      ]
                  },
                  {
                      "name": "Natural Resources",
                      "type": "group",
                      "items": [{
                          "name": "Surveillance",
                          "type": "group",
                          "items": [{
                              "name": "Early Detection System and Environmental Surveillance - Madre de Dios",
                              "type": "esri-mapServer",
                              "url": "https://geoservidorperu.minam.gob.pe/arcgis/rest/services/MONITOREO_SIDETEVA/MapServer"
                          }]
                      },
                      {
                          "name": "Oil and Gas",
                          "type": "group",
                          "items": [{
                              "name": "Pipeline",
                              "type": "esri-mapServer",
                              "url": "https://geoservidorperu.minam.gob.pe/arcgis/rest/services/ServicioOleductoRuta/MapServer"
                          }]
                      }
                      ]
                  }
                  ]
              },
              {
          "name": "Instituto Geologico, Minero y Metalurgico ",
          "type": "group",
                  "items": [{
            "name": "Natural Resources",
                      "type": "group",
            "items": [{
              "name": "Minerals",
              "type": "group"
            }]
          }
          ]
        },
        {
          "name": "Red Amazónica de Información Socioambiental Georreferenciada",
          "type": "group",
                  "items": [{
            "name": "Natural Resources",
                      "type": "group",
            "items": [{
              "name": "Minerals",
              "type": "group",
              "items": [{
                "name": "Illegal Mining",
                "type": "wms-getCapabilities",
                "url": "https://geo.socioambiental.org/webadaptor2/services/PilotoGarimpo/garimpo_ilegal/MapServer/WMSServer?request=GetCapabilities&service=WMS"
              },
              {
                "name": "Mining Zones",
                "type": "wms-getCapabilities",
                "url": "https://geo.socioambiental.org/webadaptor2/services/raisg/raisg_mineria/MapServer/WMSServer?request=GetCapabilities&service=WMS"
              }
              ]
            },
            {
              "name": "Oil and Gas",
              "type": "group",
              "items": [{
                "name": "Petroleum and Gas",
                "type": "wms-getCapabilities",
                "url": "https://geo.socioambiental.org/webadaptor2/services/raisg/raisg_petroleo/MapServer/WMSServer?request=GetCapabilities&service=WMS"
              }
              ]
            },
            {
              "name": "Water",
              "type": "group",
              "items": [{
                "name": "Dams",
                "type": "wms-getCapabilities",
                "url": "https://geo.socioambiental.org/webadaptor2/services/raisg/raisg_energia/MapServer/WMSServer?request=GetCapabilities&service=WMS"
              }
              ]
            }
            ]
          }
          ]
              }
              ]
          },
          {
              "name": "Socioeconomic and Demographic",
              "type": "group",
              "order": 2,
              "description": "desc",
              "items": [{
                  "name": "Population",
                  "type": "group"
              }]
          },
          {
              "name": "Political divisions",
              "type": "group",
              "order": 3,
              "items": [{
                      "name": "Departments",
                      "type": "group"
                  },
                  {
                      "name": "Provinces",
                      "type": "group"
                  }
              ]
  
          },
          {
              "name": "Infrastructure",
              "type": "group",
              "order": 4,
              "items": [{
                  "name": "Transport",
                  "type": "group"
              }]
          },
          {
              "name": "Biodiversity and Ecosystems",
              "type": "group",
              "order": 5,
              "items": [{
                  "name": "Protected Areas",
                  "type": "group",
                  "items": [{
                      "name": "Conservation Areas",
                      "type": "esri-mapServer",
                      "url": "https://geoservidorperu.minam.gob.pe/arcgis/rest/services/ANP/MapServer"
                  },
                  {
                      "name": "Image Catalog",
                      "type": "esri-mapServer",
                      "url": "https://geoservidorperu.minam.gob.pe/arcgis/rest/services/Catalogo_Imagenes/MapServer"
                  },
                  {
                      "name": "Risk Scenarios in Piura",
                      "type": "esri-mapServer",
                      "url": "https://geoservidorperu.minam.gob.pe/arcgis/rest/services/Escenarios_riesgo_piura/MapServer"
                  }]
              },
              {
                  "name": "Coastal and Marine Ecosystems",
                  "type": "group",
                  "items": [{
                      "name": "Marine Erosion",
                      "type": "esri-mapServer",
                      "url": "https://geoservidorperu.minam.gob.pe/arcgis/rest/services/ServicioGeocostaErosion/MapServer"
                  },
                  {
                      "name": "Southeast Pacific data and Information Network in support to Integrated Coastal Area Management",
                      "type": "esri-mapServer",
                      "url": "https://geoservidorperu.minam.gob.pe/arcgis/rest/services/ServicioIndicadores/MapServer"
                  },
                  {
                      "name": "Coastal Marine Ecosystem",
                      "type": "esri-mapServer",
                      "url": "https://geoservidorperu.minam.gob.pe/arcgis/rest/services/ServicioGeocostaEcosistema/MapServer"
                  }
                  ]
              },
              {
                  "name": "Vegetation and Land Cover",
                  "type": "group",
                  "items": [{
                      "name": "Carbon",
                      "type": "esri-mapServer",
                      "url": "https://geoservidorperu.minam.gob.pe/arcgis/rest/services/ServicioCarbono/MapServer"
                  }]
              }
          ]
          },
          {
              "name": "Disaster",
              "type": "group",
              "order": 6,
              "items": [{
                  "name": "Floods",
                  "type": "group"
              }]
          },
          {
              "name": "Infrastructure",
              "type": "group",
              "order": 7
          },
          {
              "name": "Natural Resources",
              "type": "group",
              "order": 8,
              "items": [{
                  "name": "Water",
                  "type": "group",
                  "items": [{
                          "name": "Potable Water",
                          "type": "group",
                          "items": [{
                              "name": "Centros_Potabilizacion",
                              "type": "esri-mapServer",
                              "url": "https://dportalgis.vivienda.gob.pe/dfdserver/rest/services/OGEI/Centros_Potabilizacion/MapServer"
                          }]
                      },
                      {
                          "name": "Sanitation",
                          "type": "group",
                          "items": [{
                              "name": "Componentes_de_proyecto_de_saneamiento",
                              "type": "esri-mapServer",
                              "url": "https://dportalgis.vivienda.gob.pe/dfdserver/rest/services/OGEI/Componentes_de_proyecto_de_saneamiento/MapServer"
                          }]
                      }
                  ]
              },
              {
                  "name": "Surveillance",
                  "type": "group",
                  "items": [{
                      "name": "Early Detection System and Environmental Surveillance - Madre de Dios",
                      "type": "esri-mapServer",
                      "url": "https://geoservidorperu.minam.gob.pe/arcgis/rest/services/MONITOREO_SIDETEVA/MapServer"
                  }]
              },
              {
                  "name": "Oil and Gas",
                  "type": "group",
                  "items": [{
                      "name": "Pipeline",
                      "type": "esri-mapServer",
                      "url": "https://geoservidorperu.minam.gob.pe/arcgis/rest/services/ServicioOleductoRuta/MapServer"
                  }]
              }
              ]
          }]
  }
  